{
    "brands":[
        {
            "shop_no":1,
            "brand_code":"B000000G",
            "brand_name":"\uccb4\ub808\ubbf8 \ub9c8\uce74",
            "use_brand":"T",
            "search_keyword":"\uccb4\ub808\ubbf8 \ub9c8\uce74, \uc774\ube0c",
            "product_count":0,
            "created_date":"2022-07-07T21:27:47+09:00"
        },
        {
            "shop_no":1,
            "brand_code":"B000000A",
            "brand_name":"\ucf58\ub3d4",
            "use_brand":"T",
            "search_keyword":"",
            "product_count":0,
            "created_date":"2020-06-05T15:39:13+09:00"
        },
        {
            "shop_no":1,
            "brand_code":"B0000000",
            "brand_name":"EVE",
            "use_brand":"T",
            "search_keyword":"",
            "product_count":403,
            "created_date":"2019-02-12T14:02:43+09:00"
        }
    ]
}
